{
    "data": {
        "repository": {
            "forks": {
                "totalCount": 401,
                "nodes": [
                    {
                        "nameWithOwner": "jessenboone/employee-manager",
                        "url": "https://github.com/jessenboone/employee-manager",
                        "createdAt": "2017-05-17T15:38:10Z",
                        "defaultBranchRef": {
                            "target": {
                                "committedDate": "2017-05-09T15:37:27Z"
                            }
                        }
                    },
                    {
                        "nameWithOwner": "joeblank/employee-manager",
                        "url": "https://github.com/joeblank/employee-manager",
                        "createdAt": "2017-05-17T18:12:34Z",
                        "defaultBranchRef": {
                            "target": {
                                "committedDate": "2017-05-09T15:37:27Z"
                            }
                        }
                    },
                    {
                        "nameWithOwner": "Carlos118920/employee-manager",
                        "url": "https://github.com/Carlos118920/employee-manager",
                        "createdAt": "2017-05-17T21:26:05Z",
                        "defaultBranchRef": {
                            "target": {
                                "committedDate": "2017-05-09T15:37:27Z"
                            }
                        }
                    },
                    {
                        "nameWithOwner": "codingplumber/employee-manager",
                        "url": "https://github.com/codingplumber/employee-manager",
                        "createdAt": "2017-05-17T21:52:21Z",
                        "defaultBranchRef": {
                            "target": {
                                "committedDate": "2017-05-09T15:37:27Z"
                            }
                        }
                    },
                    {
                        "nameWithOwner": "ZMcClung88/employee-manager",
                        "url": "https://github.com/ZMcClung88/employee-manager",
                        "createdAt": "2017-05-18T04:28:58Z",
                        "defaultBranchRef": {
                            "target": {
                                "committedDate": "2017-05-09T15:37:27Z"
                            }
                        }
                    },
                    {
                        "nameWithOwner": "yohannisberg/employee-manager",
                        "url": "https://github.com/yohannisberg/employee-manager",
                        "createdAt": "2017-05-18T15:19:54Z",
                        "defaultBranchRef": {
                            "target": {
                                "committedDate": "2017-05-09T15:37:27Z"
                            }
                        }
                    },
                    {
                        "nameWithOwner": "TheSeventhLion/employee-manager",
                        "url": "https://github.com/TheSeventhLion/employee-manager",
                        "createdAt": "2017-05-18T15:28:54Z",
                        "defaultBranchRef": {
                            "target": {
                                "committedDate": "2017-05-09T15:37:27Z"
                            }
                        }
                    },
                    {
                        "nameWithOwner": "dallin-r-parker/employee-manager",
                        "url": "https://github.com/dallin-r-parker/employee-manager",
                        "createdAt": "2017-05-24T21:56:55Z",
                        "defaultBranchRef": {
                            "target": {
                                "committedDate": "2017-05-09T15:37:27Z"
                            }
                        }
                    },
                    {
                        "nameWithOwner": "GL-A/employee-manager",
                        "url": "https://github.com/GL-A/employee-manager",
                        "createdAt": "2017-06-08T20:24:40Z",
                        "defaultBranchRef": {
                            "target": {
                                "committedDate": "2017-07-05T22:00:04Z"
                            }
                        }
                    },
                    {
                        "nameWithOwner": "Justiceleeg/employee-manager",
                        "url": "https://github.com/Justiceleeg/employee-manager",
                        "createdAt": "2017-06-13T02:57:04Z",
                        "defaultBranchRef": {
                            "target": {
                                "committedDate": "2017-06-14T00:08:17Z"
                            }
                        }
                    },
                    {
                        "nameWithOwner": "bluecherryme/employee-manager",
                        "url": "https://github.com/bluecherryme/employee-manager",
                        "createdAt": "2017-06-13T03:28:27Z",
                        "defaultBranchRef": {
                            "target": {
                                "committedDate": "2017-05-09T15:37:27Z"
                            }
                        }
                    },
                    {
                        "nameWithOwner": "mitch-foster/employee-manager",
                        "url": "https://github.com/mitch-foster/employee-manager",
                        "createdAt": "2017-06-13T03:51:42Z",
                        "defaultBranchRef": {
                            "target": {
                                "committedDate": "2017-06-13T23:10:43Z"
                            }
                        }
                    },
                    {
                        "nameWithOwner": "dontimoteo21/employee-manager",
                        "url": "https://github.com/dontimoteo21/employee-manager",
                        "createdAt": "2017-06-13T15:13:06Z",
                        "defaultBranchRef": {
                            "target": {
                                "committedDate": "2017-06-14T12:55:25Z"
                            }
                        }
                    },
                    {
                        "nameWithOwner": "bethtelford/employee-manager",
                        "url": "https://github.com/bethtelford/employee-manager",
                        "createdAt": "2017-06-13T15:48:16Z",
                        "defaultBranchRef": {
                            "target": {
                                "committedDate": "2017-06-13T22:45:42Z"
                            }
                        }
                    },
                    {
                        "nameWithOwner": "jesse10e/employee-manager",
                        "url": "https://github.com/jesse10e/employee-manager",
                        "createdAt": "2017-06-13T16:05:13Z",
                        "defaultBranchRef": {
                            "target": {
                                "committedDate": "2017-05-09T15:37:27Z"
                            }
                        }
                    },
                    {
                        "nameWithOwner": "nkaleigh/employee-manager",
                        "url": "https://github.com/nkaleigh/employee-manager",
                        "createdAt": "2017-06-13T16:07:49Z",
                        "defaultBranchRef": {
                            "target": {
                                "committedDate": "2017-06-13T20:05:11Z"
                            }
                        }
                    },
                    {
                        "nameWithOwner": "jaygraygray/employee-manager",
                        "url": "https://github.com/jaygraygray/employee-manager",
                        "createdAt": "2017-06-13T17:18:16Z",
                        "defaultBranchRef": {
                            "target": {
                                "committedDate": "2017-06-18T00:11:53Z"
                            }
                        }
                    },
                    {
                        "nameWithOwner": "rnoelle/employee-manager",
                        "url": "https://github.com/rnoelle/employee-manager",
                        "createdAt": "2017-06-13T17:27:22Z",
                        "defaultBranchRef": {
                            "target": {
                                "committedDate": "2017-06-13T21:31:54Z"
                            }
                        }
                    },
                    {
                        "nameWithOwner": "lpabst/employee-manager",
                        "url": "https://github.com/lpabst/employee-manager",
                        "createdAt": "2017-06-13T18:39:31Z",
                        "defaultBranchRef": {
                            "target": {
                                "committedDate": "2017-06-13T22:29:40Z"
                            }
                        }
                    },
                    {
                        "nameWithOwner": "jdpabst/employee-manager",
                        "url": "https://github.com/jdpabst/employee-manager",
                        "createdAt": "2017-06-13T19:08:16Z",
                        "defaultBranchRef": {
                            "target": {
                                "committedDate": "2017-06-13T22:06:28Z"
                            }
                        }
                    },
                    {
                        "nameWithOwner": "ivorjanderson/employee-manager",
                        "url": "https://github.com/ivorjanderson/employee-manager",
                        "createdAt": "2017-06-13T19:08:22Z",
                        "defaultBranchRef": {
                            "target": {
                                "committedDate": "2017-05-09T15:37:27Z"
                            }
                        }
                    },
                    {
                        "nameWithOwner": "nturner5/employee-manager",
                        "url": "https://github.com/nturner5/employee-manager",
                        "createdAt": "2017-06-13T19:09:33Z",
                        "defaultBranchRef": {
                            "target": {
                                "committedDate": "2017-05-09T15:37:27Z"
                            }
                        }
                    },
                    {
                        "nameWithOwner": "davidtagholmes/employee-manager",
                        "url": "https://github.com/davidtagholmes/employee-manager",
                        "createdAt": "2017-06-13T19:16:51Z",
                        "defaultBranchRef": {
                            "target": {
                                "committedDate": "2017-05-09T15:37:27Z"
                            }
                        }
                    },
                    {
                        "nameWithOwner": "ehuntsman/employee-manager",
                        "url": "https://github.com/ehuntsman/employee-manager",
                        "createdAt": "2017-06-13T19:32:56Z",
                        "defaultBranchRef": {
                            "target": {
                                "committedDate": "2017-06-13T22:10:17Z"
                            }
                        }
                    },
                    {
                        "nameWithOwner": "Vicki1/employee-manager",
                        "url": "https://github.com/Vicki1/employee-manager",
                        "createdAt": "2017-06-13T19:34:44Z",
                        "defaultBranchRef": {
                            "target": {
                                "committedDate": "2017-05-09T15:37:27Z"
                            }
                        }
                    },
                    {
                        "nameWithOwner": "NDMueller/employee-manager",
                        "url": "https://github.com/NDMueller/employee-manager",
                        "createdAt": "2017-06-13T19:37:01Z",
                        "defaultBranchRef": {
                            "target": {
                                "committedDate": "2017-06-13T21:39:46Z"
                            }
                        }
                    },
                    {
                        "nameWithOwner": "eliKeetch/employee-manager",
                        "url": "https://github.com/eliKeetch/employee-manager",
                        "createdAt": "2017-06-13T19:38:57Z",
                        "defaultBranchRef": {
                            "target": {
                                "committedDate": "2017-05-09T15:37:27Z"
                            }
                        }
                    },
                    {
                        "nameWithOwner": "jordanfuzz/employee-manager",
                        "url": "https://github.com/jordanfuzz/employee-manager",
                        "createdAt": "2017-06-13T19:39:16Z",
                        "defaultBranchRef": {
                            "target": {
                                "committedDate": "2017-05-09T15:37:27Z"
                            }
                        }
                    },
                    {
                        "nameWithOwner": "AlexHill5/employee-manager",
                        "url": "https://github.com/AlexHill5/employee-manager",
                        "createdAt": "2017-06-13T19:39:23Z",
                        "defaultBranchRef": {
                            "target": {
                                "committedDate": "2017-06-13T23:45:34Z"
                            }
                        }
                    },
                    {
                        "nameWithOwner": "ricco1337/employee-manager",
                        "url": "https://github.com/ricco1337/employee-manager",
                        "createdAt": "2017-06-13T19:39:34Z",
                        "defaultBranchRef": {
                            "target": {
                                "committedDate": "2017-05-09T15:37:27Z"
                            }
                        }
                    },
                    {
                        "nameWithOwner": "rustonrr/employee-manager",
                        "url": "https://github.com/rustonrr/employee-manager",
                        "createdAt": "2017-06-13T19:40:30Z",
                        "defaultBranchRef": {
                            "target": {
                                "committedDate": "2017-05-09T15:37:27Z"
                            }
                        }
                    },
                    {
                        "nameWithOwner": "joej326/employee-manager",
                        "url": "https://github.com/joej326/employee-manager",
                        "createdAt": "2017-06-13T19:40:54Z",
                        "defaultBranchRef": {
                            "target": {
                                "committedDate": "2017-05-09T15:37:27Z"
                            }
                        }
                    },
                    {
                        "nameWithOwner": "TBosh/employee-manager",
                        "url": "https://github.com/TBosh/employee-manager",
                        "createdAt": "2017-06-13T19:40:55Z",
                        "defaultBranchRef": {
                            "target": {
                                "committedDate": "2017-05-09T15:37:27Z"
                            }
                        }
                    },
                    {
                        "nameWithOwner": "gswensen/employee-manager",
                        "url": "https://github.com/gswensen/employee-manager",
                        "createdAt": "2017-06-13T19:41:28Z",
                        "defaultBranchRef": {
                            "target": {
                                "committedDate": "2017-05-09T15:37:27Z"
                            }
                        }
                    },
                    {
                        "nameWithOwner": "Nephaelin/employee-manager",
                        "url": "https://github.com/Nephaelin/employee-manager",
                        "createdAt": "2017-06-13T19:41:47Z",
                        "defaultBranchRef": {
                            "target": {
                                "committedDate": "2017-05-09T15:37:27Z"
                            }
                        }
                    },
                    {
                        "nameWithOwner": "briandinhtran/employee-manager",
                        "url": "https://github.com/briandinhtran/employee-manager",
                        "createdAt": "2017-06-13T19:43:22Z",
                        "defaultBranchRef": {
                            "target": {
                                "committedDate": "2017-05-09T15:37:27Z"
                            }
                        }
                    },
                    {
                        "nameWithOwner": "chrnzhng/employee-manager",
                        "url": "https://github.com/chrnzhng/employee-manager",
                        "createdAt": "2017-06-13T19:44:11Z",
                        "defaultBranchRef": {
                            "target": {
                                "committedDate": "2017-06-13T22:32:55Z"
                            }
                        }
                    },
                    {
                        "nameWithOwner": "erpatterson11/employee-manager",
                        "url": "https://github.com/erpatterson11/employee-manager",
                        "createdAt": "2017-06-13T19:44:30Z",
                        "defaultBranchRef": {
                            "target": {
                                "committedDate": "2017-05-09T15:37:27Z"
                            }
                        }
                    },
                    {
                        "nameWithOwner": "iAmYeko/employee-manager",
                        "url": "https://github.com/iAmYeko/employee-manager",
                        "createdAt": "2017-06-13T19:45:15Z",
                        "defaultBranchRef": {
                            "target": {
                                "committedDate": "2017-05-09T15:37:27Z"
                            }
                        }
                    },
                    {
                        "nameWithOwner": "brandons9062/employee-manager",
                        "url": "https://github.com/brandons9062/employee-manager",
                        "createdAt": "2017-06-13T19:45:22Z",
                        "defaultBranchRef": {
                            "target": {
                                "committedDate": "2017-06-13T22:40:33Z"
                            }
                        }
                    },
                    {
                        "nameWithOwner": "actualchandler/employee-manager",
                        "url": "https://github.com/actualchandler/employee-manager",
                        "createdAt": "2017-06-13T19:45:42Z",
                        "defaultBranchRef": {
                            "target": {
                                "committedDate": "2017-05-09T15:37:27Z"
                            }
                        }
                    },
                    {
                        "nameWithOwner": "ashlyndanielle/employee-manager",
                        "url": "https://github.com/ashlyndanielle/employee-manager",
                        "createdAt": "2017-06-13T19:46:19Z",
                        "defaultBranchRef": {
                            "target": {
                                "committedDate": "2017-05-09T15:37:27Z"
                            }
                        }
                    },
                    {
                        "nameWithOwner": "robinsonnathan/employee-manager",
                        "url": "https://github.com/robinsonnathan/employee-manager",
                        "createdAt": "2017-06-13T19:46:25Z",
                        "defaultBranchRef": {
                            "target": {
                                "committedDate": "2017-05-09T15:37:27Z"
                            }
                        }
                    },
                    {
                        "nameWithOwner": "adamfigg/employee-manager",
                        "url": "https://github.com/adamfigg/employee-manager",
                        "createdAt": "2017-06-13T19:46:27Z",
                        "defaultBranchRef": {
                            "target": {
                                "committedDate": "2017-05-09T15:37:27Z"
                            }
                        }
                    },
                    {
                        "nameWithOwner": "pchiarato/employee-manager",
                        "url": "https://github.com/pchiarato/employee-manager",
                        "createdAt": "2017-06-13T19:50:03Z",
                        "defaultBranchRef": {
                            "target": {
                                "committedDate": "2017-05-09T15:37:27Z"
                            }
                        }
                    },
                    {
                        "nameWithOwner": "black-penguin/employee-manager",
                        "url": "https://github.com/black-penguin/employee-manager",
                        "createdAt": "2017-06-13T19:50:46Z",
                        "defaultBranchRef": {
                            "target": {
                                "committedDate": "2017-06-13T20:58:35Z"
                            }
                        }
                    },
                    {
                        "nameWithOwner": "jesspoemape/employee-manager",
                        "url": "https://github.com/jesspoemape/employee-manager",
                        "createdAt": "2017-06-19T01:57:37Z",
                        "defaultBranchRef": {
                            "target": {
                                "committedDate": "2017-06-14T00:13:02Z"
                            }
                        }
                    },
                    {
                        "nameWithOwner": "MeganMFisher/employee-manager",
                        "url": "https://github.com/MeganMFisher/employee-manager",
                        "createdAt": "2017-06-27T20:14:27Z",
                        "defaultBranchRef": {
                            "target": {
                                "committedDate": "2017-06-14T00:13:02Z"
                            }
                        }
                    },
                    {
                        "nameWithOwner": "ikhem/employee-manager",
                        "url": "https://github.com/ikhem/employee-manager",
                        "createdAt": "2017-07-05T01:17:34Z",
                        "defaultBranchRef": {
                            "target": {
                                "committedDate": "2017-07-05T22:50:10Z"
                            }
                        }
                    },
                    {
                        "nameWithOwner": "missyjeanbeutler/employee-manager",
                        "url": "https://github.com/missyjeanbeutler/employee-manager",
                        "createdAt": "2017-07-05T19:06:18Z",
                        "defaultBranchRef": {
                            "target": {
                                "committedDate": "2017-07-05T22:59:20Z"
                            }
                        }
                    },
                    {
                        "nameWithOwner": "jodilark/employee-manager",
                        "url": "https://github.com/jodilark/employee-manager",
                        "createdAt": "2017-07-05T19:57:08Z",
                        "defaultBranchRef": {
                            "target": {
                                "committedDate": "2017-07-05T22:42:43Z"
                            }
                        }
                    },
                    {
                        "nameWithOwner": "sargent88/employee-manager",
                        "url": "https://github.com/sargent88/employee-manager",
                        "createdAt": "2017-07-05T19:58:49Z",
                        "defaultBranchRef": {
                            "target": {
                                "committedDate": "2017-06-14T00:13:02Z"
                            }
                        }
                    },
                    {
                        "nameWithOwner": "brockpettyjohn/employee-manager",
                        "url": "https://github.com/brockpettyjohn/employee-manager",
                        "createdAt": "2017-07-05T20:00:59Z",
                        "defaultBranchRef": {
                            "target": {
                                "committedDate": "2017-06-14T00:13:02Z"
                            }
                        }
                    },
                    {
                        "nameWithOwner": "daveguymon/employee-manager",
                        "url": "https://github.com/daveguymon/employee-manager",
                        "createdAt": "2017-07-05T20:10:06Z",
                        "defaultBranchRef": {
                            "target": {
                                "committedDate": "2017-07-06T03:49:23Z"
                            }
                        }
                    },
                    {
                        "nameWithOwner": "taylormckay68/employee-manager",
                        "url": "https://github.com/taylormckay68/employee-manager",
                        "createdAt": "2017-07-05T20:34:48Z",
                        "defaultBranchRef": {
                            "target": {
                                "committedDate": "2017-06-14T00:13:02Z"
                            }
                        }
                    },
                    {
                        "nameWithOwner": "sevensidedsilver/employee-manager",
                        "url": "https://github.com/sevensidedsilver/employee-manager",
                        "createdAt": "2017-07-05T20:38:00Z",
                        "defaultBranchRef": {
                            "target": {
                                "committedDate": "2017-06-14T00:13:02Z"
                            }
                        }
                    },
                    {
                        "nameWithOwner": "murffious/employee-manager",
                        "url": "https://github.com/murffious/employee-manager",
                        "createdAt": "2017-07-05T20:38:52Z",
                        "defaultBranchRef": {
                            "target": {
                                "committedDate": "2017-06-14T00:13:02Z"
                            }
                        }
                    },
                    {
                        "nameWithOwner": "cmwilson88/employee-manager",
                        "url": "https://github.com/cmwilson88/employee-manager",
                        "createdAt": "2017-07-05T20:39:53Z",
                        "defaultBranchRef": {
                            "target": {
                                "committedDate": "2017-06-14T00:13:02Z"
                            }
                        }
                    },
                    {
                        "nameWithOwner": "huyqdang/employee-manager",
                        "url": "https://github.com/huyqdang/employee-manager",
                        "createdAt": "2017-07-05T20:40:00Z",
                        "defaultBranchRef": {
                            "target": {
                                "committedDate": "2017-06-14T00:13:02Z"
                            }
                        }
                    },
                    {
                        "nameWithOwner": "KScarabello/employee-manager",
                        "url": "https://github.com/KScarabello/employee-manager",
                        "createdAt": "2017-07-05T20:53:56Z",
                        "defaultBranchRef": {
                            "target": {
                                "committedDate": "2017-06-14T00:13:02Z"
                            }
                        }
                    },
                    {
                        "nameWithOwner": "joshwilcken/employee-manager",
                        "url": "https://github.com/joshwilcken/employee-manager",
                        "createdAt": "2017-07-05T20:54:32Z",
                        "defaultBranchRef": {
                            "target": {
                                "committedDate": "2017-06-14T00:13:02Z"
                            }
                        }
                    },
                    {
                        "nameWithOwner": "Dallin11/employee-manager",
                        "url": "https://github.com/Dallin11/employee-manager",
                        "createdAt": "2017-07-05T21:05:08Z",
                        "defaultBranchRef": {
                            "target": {
                                "committedDate": "2017-06-14T00:13:02Z"
                            }
                        }
                    },
                    {
                        "nameWithOwner": "kellaisene/employee-manager",
                        "url": "https://github.com/kellaisene/employee-manager",
                        "createdAt": "2017-07-05T21:12:06Z",
                        "defaultBranchRef": {
                            "target": {
                                "committedDate": "2017-07-05T23:24:34Z"
                            }
                        }
                    },
                    {
                        "nameWithOwner": "Yzhou2/employee-manager",
                        "url": "https://github.com/Yzhou2/employee-manager",
                        "createdAt": "2017-07-05T21:18:05Z",
                        "defaultBranchRef": {
                            "target": {
                                "committedDate": "2017-07-06T02:01:30Z"
                            }
                        }
                    },
                    {
                        "nameWithOwner": "carter-t/employee-manager",
                        "url": "https://github.com/carter-t/employee-manager",
                        "createdAt": "2017-07-05T21:18:36Z",
                        "defaultBranchRef": {
                            "target": {
                                "committedDate": "2017-06-14T00:13:02Z"
                            }
                        }
                    },
                    {
                        "nameWithOwner": "ashleyschuette/employee-manager",
                        "url": "https://github.com/ashleyschuette/employee-manager",
                        "createdAt": "2017-07-05T21:23:02Z",
                        "defaultBranchRef": {
                            "target": {
                                "committedDate": "2017-06-14T00:13:02Z"
                            }
                        }
                    },
                    {
                        "nameWithOwner": "ttluan411-zz/employee-manager",
                        "url": "https://github.com/ttluan411-zz/employee-manager",
                        "createdAt": "2017-07-05T21:28:49Z",
                        "defaultBranchRef": {
                            "target": {
                                "committedDate": "2017-07-05T22:44:42Z"
                            }
                        }
                    },
                    {
                        "nameWithOwner": "fieldsmatt86/employee-manager",
                        "url": "https://github.com/fieldsmatt86/employee-manager",
                        "createdAt": "2017-07-05T21:44:24Z",
                        "defaultBranchRef": {
                            "target": {
                                "committedDate": "2017-06-14T00:13:02Z"
                            }
                        }
                    },
                    {
                        "nameWithOwner": "claytonpabst/employee-manager",
                        "url": "https://github.com/claytonpabst/employee-manager",
                        "createdAt": "2017-07-05T22:47:12Z",
                        "defaultBranchRef": {
                            "target": {
                                "committedDate": "2017-06-14T00:13:02Z"
                            }
                        }
                    },
                    {
                        "nameWithOwner": "jaydray1/employee-manager",
                        "url": "https://github.com/jaydray1/employee-manager",
                        "createdAt": "2017-07-06T20:10:22Z",
                        "defaultBranchRef": {
                            "target": {
                                "committedDate": "2017-12-26T21:24:18Z"
                            }
                        }
                    },
                    {
                        "nameWithOwner": "DevMountain-QA/early-enter-wanted",
                        "url": "https://github.com/DevMountain-QA/early-enter-wanted",
                        "createdAt": "2017-07-18T21:08:34Z",
                        "defaultBranchRef": {
                            "target": {
                                "committedDate": "2017-10-03T14:43:36Z"
                            }
                        }
                    },
                    {
                        "nameWithOwner": "janises/employee-manager",
                        "url": "https://github.com/janises/employee-manager",
                        "createdAt": "2017-08-01T05:08:34Z",
                        "defaultBranchRef": {
                            "target": {
                                "committedDate": "2017-08-01T22:11:56Z"
                            }
                        }
                    },
                    {
                        "nameWithOwner": "kikoro86us/employee-manager",
                        "url": "https://github.com/kikoro86us/employee-manager",
                        "createdAt": "2017-08-01T07:16:25Z",
                        "defaultBranchRef": {
                            "target": {
                                "committedDate": "2017-06-14T00:13:02Z"
                            }
                        }
                    },
                    {
                        "nameWithOwner": "ClassyFD/employee-manager",
                        "url": "https://github.com/ClassyFD/employee-manager",
                        "createdAt": "2017-08-01T16:10:14Z",
                        "defaultBranchRef": {
                            "target": {
                                "committedDate": "2017-06-14T00:13:02Z"
                            }
                        }
                    },
                    {
                        "nameWithOwner": "mahburg/employee-manager",
                        "url": "https://github.com/mahburg/employee-manager",
                        "createdAt": "2017-08-01T18:08:16Z",
                        "defaultBranchRef": {
                            "target": {
                                "committedDate": "2017-08-01T19:29:49Z"
                            }
                        }
                    },
                    {
                        "nameWithOwner": "yabbbs/employee-manager",
                        "url": "https://github.com/yabbbs/employee-manager",
                        "createdAt": "2017-08-01T19:00:37Z",
                        "defaultBranchRef": {
                            "target": {
                                "committedDate": "2017-08-01T21:26:59Z"
                            }
                        }
                    },
                    {
                        "nameWithOwner": "Aortizv7/employee-manager",
                        "url": "https://github.com/Aortizv7/employee-manager",
                        "createdAt": "2017-08-01T19:35:14Z",
                        "defaultBranchRef": {
                            "target": {
                                "committedDate": "2017-11-08T01:25:08Z"
                            }
                        }
                    },
                    {
                        "nameWithOwner": "Chris502/employee-manager",
                        "url": "https://github.com/Chris502/employee-manager",
                        "createdAt": "2017-08-01T19:40:07Z",
                        "defaultBranchRef": {
                            "target": {
                                "committedDate": "2017-06-14T00:13:02Z"
                            }
                        }
                    },
                    {
                        "nameWithOwner": "Johnivie141/employee-manager",
                        "url": "https://github.com/Johnivie141/employee-manager",
                        "createdAt": "2017-08-01T19:44:21Z",
                        "defaultBranchRef": {
                            "target": {
                                "committedDate": "2017-06-14T00:13:02Z"
                            }
                        }
                    },
                    {
                        "nameWithOwner": "emkeator/employee-manager",
                        "url": "https://github.com/emkeator/employee-manager",
                        "createdAt": "2017-08-01T19:52:01Z",
                        "defaultBranchRef": {
                            "target": {
                                "committedDate": "2017-08-01T21:48:13Z"
                            }
                        }
                    },
                    {
                        "nameWithOwner": "niraj154/employee-manager",
                        "url": "https://github.com/niraj154/employee-manager",
                        "createdAt": "2017-08-01T19:56:20Z",
                        "defaultBranchRef": {
                            "target": {
                                "committedDate": "2017-06-14T00:13:02Z"
                            }
                        }
                    },
                    {
                        "nameWithOwner": "seanqureshi/employee-manager",
                        "url": "https://github.com/seanqureshi/employee-manager",
                        "createdAt": "2017-08-01T20:21:16Z",
                        "defaultBranchRef": {
                            "target": {
                                "committedDate": "2017-10-03T14:34:18Z"
                            }
                        }
                    },
                    {
                        "nameWithOwner": "andiplatter/employee-manager",
                        "url": "https://github.com/andiplatter/employee-manager",
                        "createdAt": "2017-08-01T20:31:08Z",
                        "defaultBranchRef": {
                            "target": {
                                "committedDate": "2017-06-14T00:13:02Z"
                            }
                        }
                    },
                    {
                        "nameWithOwner": "CharlesMurphy94/employee-manager",
                        "url": "https://github.com/CharlesMurphy94/employee-manager",
                        "createdAt": "2017-08-01T20:47:23Z",
                        "defaultBranchRef": {
                            "target": {
                                "committedDate": "2017-06-14T00:13:02Z"
                            }
                        }
                    },
                    {
                        "nameWithOwner": "blairwoodward57/employee-manager",
                        "url": "https://github.com/blairwoodward57/employee-manager",
                        "createdAt": "2017-08-01T21:40:26Z",
                        "defaultBranchRef": {
                            "target": {
                                "committedDate": "2017-06-14T00:13:02Z"
                            }
                        }
                    },
                    {
                        "nameWithOwner": "FreeFlight-Code/employee-manager",
                        "url": "https://github.com/FreeFlight-Code/employee-manager",
                        "createdAt": "2017-08-02T03:28:31Z",
                        "defaultBranchRef": {
                            "target": {
                                "committedDate": "2017-06-14T00:13:02Z"
                            }
                        }
                    },
                    {
                        "nameWithOwner": "Rhayme/employee-manager",
                        "url": "https://github.com/Rhayme/employee-manager",
                        "createdAt": "2017-08-04T01:16:45Z",
                        "defaultBranchRef": {
                            "target": {
                                "committedDate": "2017-06-14T00:13:02Z"
                            }
                        }
                    },
                    {
                        "nameWithOwner": "elderlowell/employee-manager",
                        "url": "https://github.com/elderlowell/employee-manager",
                        "createdAt": "2017-08-04T01:20:42Z",
                        "defaultBranchRef": {
                            "target": {
                                "committedDate": "2017-06-14T00:13:02Z"
                            }
                        }
                    },
                    {
                        "nameWithOwner": "jboucher8/employee-manager",
                        "url": "https://github.com/jboucher8/employee-manager",
                        "createdAt": "2017-08-04T01:23:22Z",
                        "defaultBranchRef": {
                            "target": {
                                "committedDate": "2017-08-04T02:51:57Z"
                            }
                        }
                    },
                    {
                        "nameWithOwner": "chegior/employee-manager",
                        "url": "https://github.com/chegior/employee-manager",
                        "createdAt": "2017-08-04T01:24:51Z",
                        "defaultBranchRef": {
                            "target": {
                                "committedDate": "2017-06-14T00:13:02Z"
                            }
                        }
                    },
                    {
                        "nameWithOwner": "jhuppe/employee-manager",
                        "url": "https://github.com/jhuppe/employee-manager",
                        "createdAt": "2017-08-04T01:27:37Z",
                        "defaultBranchRef": {
                            "target": {
                                "committedDate": "2017-08-04T02:58:44Z"
                            }
                        }
                    },
                    {
                        "nameWithOwner": "Dallin09/employee-manager",
                        "url": "https://github.com/Dallin09/employee-manager",
                        "createdAt": "2017-08-05T16:56:05Z",
                        "defaultBranchRef": {
                            "target": {
                                "committedDate": "2017-06-14T00:13:02Z"
                            }
                        }
                    },
                    {
                        "nameWithOwner": "ryand825/employee-manager",
                        "url": "https://github.com/ryand825/employee-manager",
                        "createdAt": "2017-08-09T00:26:05Z",
                        "defaultBranchRef": {
                            "target": {
                                "committedDate": "2017-08-09T02:45:25Z"
                            }
                        }
                    },
                    {
                        "nameWithOwner": "bpluim/employee-manager",
                        "url": "https://github.com/bpluim/employee-manager",
                        "createdAt": "2017-08-11T01:14:28Z",
                        "defaultBranchRef": {
                            "target": {
                                "committedDate": "2017-06-14T00:13:02Z"
                            }
                        }
                    },
                    {
                        "nameWithOwner": "CoquiFrog/employee-manager",
                        "url": "https://github.com/CoquiFrog/employee-manager",
                        "createdAt": "2017-08-14T16:12:19Z",
                        "defaultBranchRef": {
                            "target": {
                                "committedDate": "2017-06-14T00:13:02Z"
                            }
                        }
                    },
                    {
                        "nameWithOwner": "Caccavella/employee-manager",
                        "url": "https://github.com/Caccavella/employee-manager",
                        "createdAt": "2017-08-14T18:00:11Z",
                        "defaultBranchRef": {
                            "target": {
                                "committedDate": "2017-08-14T22:05:02Z"
                            }
                        }
                    },
                    {
                        "nameWithOwner": "kswensen/employee-manager",
                        "url": "https://github.com/kswensen/employee-manager",
                        "createdAt": "2017-08-14T18:16:47Z",
                        "defaultBranchRef": {
                            "target": {
                                "committedDate": "2017-08-14T22:29:08Z"
                            }
                        }
                    },
                    {
                        "nameWithOwner": "ShawnKoga/employee-manager",
                        "url": "https://github.com/ShawnKoga/employee-manager",
                        "createdAt": "2017-08-14T19:01:59Z",
                        "defaultBranchRef": {
                            "target": {
                                "committedDate": "2017-08-15T00:18:42Z"
                            }
                        }
                    },
                    {
                        "nameWithOwner": "keithdidier/employee-manager",
                        "url": "https://github.com/keithdidier/employee-manager",
                        "createdAt": "2017-08-14T19:06:40Z",
                        "defaultBranchRef": {
                            "target": {
                                "committedDate": "2017-06-14T00:13:02Z"
                            }
                        }
                    },
                    {
                        "nameWithOwner": "alecjacksn/employee-manager",
                        "url": "https://github.com/alecjacksn/employee-manager",
                        "createdAt": "2017-08-14T19:08:11Z",
                        "defaultBranchRef": {
                            "target": {
                                "committedDate": "2017-06-14T00:13:02Z"
                            }
                        }
                    }
                ],
                "pageInfo": {
                    "endCursor": "Y3Vyc29yOnYyOpHOBfp37Q==",
                    "hasNextPage": true
                }
            }
        }
    }
}